rqinfo
rq_cli
