Metadata-Version: 1.0
Name: rq-cli
Version: 0.1.1
Summary: A RQ CLI tool
Home-page: https://github.com/zhangliyong/rq-cli
Author: Lyon Zhang
Author-email: lyzhang87@gmail.com
License: BSD
Platform: UNKNOWN
